[
    {
        "customer_name": "demo demo",
        "order_id": "1032",
        "timestamp": "Jan 20 at\r\n7:42 pm",
        "customer_address": "demo demo\nPune Railway Station Agarkar Nagar\nPune,\nMaharashtra\n411001\nIndia\n+919876543218",
        "customer_email": "demo@gmail.com"
    },
    {
        "customer_name": "demo demo",
        "order_id": "1033",
        "timestamp": "Jan 20 at\r\n7:43 pm",
        "customer_address": "demo demo\nPune Railway Station Agarkar Nagar\nPune,\nMaharashtra\n411001\nIndia\n+919876543218",
        "customer_email": "demo@gmail.com"
    },
    {
        "customer_name": "demo demo",
        "order_id": "1034",
        "timestamp": "Jan 20 at\r\n7:44 pm",
        "customer_address": "demo demo\nPune Railway Station Agarkar Nagar\nPune,\nMaharashtra\n411001\nIndia\n+919876543218",
        "customer_email": "demo@gmail.com"
    }
]